<tool id="SAGA.ta_compound.0" name="Basic Terrain Analysis" version="1.0.0"><description>A selection of basic parameters and objects to be derived from a Digital Terrain Model using standard settings.</description><inputs><param name="ELEVATION" label="Elevation" help="Elevation" type="text" format="image/tiff, application/x-ogc-envi, application/x-ogc-aaigrid, image/png" /><param name="THRESHOLD" label="Channel Density" help="Strahler order to begin a channel." type="integer" format="image/tiff, application/x-ogc-envi, application/x-ogc-aaigrid, image/png" /></inputs><outputs><data name="SHADE" label="Analytical Hillshading" /><data name="SLOPE" label="Slope" /><data name="ASPECT" label="Aspect" /><data name="HCURV" label="Plan Curvature" /><data name="VCURV" label="Profile Curvature" /><data name="CONVERGENCE" label="Convergence Index" /><data name="SINKS" label="Closed Depressions" /><data name="FLOW" label="Total Catchment Area" /><data name="WETNESS" label="Topographic Wetness Index" /><data name="LSFACTOR" label="LS-Factor" /><data name="CHANNELS" label="Channel Network" /><data name="BASINS" label="Drainage Basins" /><data name="CHNL_BASE" label="Channel Network Base Level" /><data name="CHNL_DIST" label="Channel Network Distance" /><data name="VALL_DEPTH" label="Valley Depth" /><data name="RSP" label="Relative Slope Position" /></outputs></tool>