<tool id="SAGA.db_odbc.5" name="Import Table" version="1.0.0"><description>Imports a table from a database via ODBC.</description><inputs><param name="ODBC_DSN" label="DSN" help="Data Source Name" type="text" /><param name="ODBC_USR" label="User" help="User Name" type="text" /><param name="ODBC_PWD" label="Password" help="Password" type="text" /><param name="CONNECTION" label="Server Connection" help="Server Connection" type="text" /><param name="TABLES" label="Tables" help="Tables" type="text" /></inputs><outputs><data name="TABLE" label="Table" /></outputs></tool>