<tool id="SAGA.ta_channels.3" name="Vertical Distance to Channel Network" version="1.0.0"><description>This tool calculates the vertical distance to a channel network base level. The algorithm consists of two major steps:&amp;lt;br/&amp;gt; 1. Interpolation of a channel network base level elevation&amp;lt;br/&amp;gt; 2. Subtraction of this base level from the original elevations&amp;lt;br/&amp;gt;</description><inputs><param name="ELEVATION" label="Elevation" help="A grid that contains elevation data." type="text" format="image/tiff, application/x-ogc-envi, application/x-ogc-aaigrid, image/png" /><param name="CHANNELS" label="Channel Network" help="A grid providing information about the channel network. It is assumed that no-data cells are not part of the channel network. Vice versa all others cells are recognised as channel network members." type="text" format="image/tiff, application/x-ogc-envi, application/x-ogc-aaigrid, image/png" /><param name="THRESHOLD" label="Tension Threshold" help="Maximum change in elevation units (e.g. meter), iteration is stopped once maximum change reaches this threshold." type="float" format="image/tiff, application/x-ogc-envi, application/x-ogc-aaigrid, image/png" /><param name="MAXITER" label="Maximum Iterations" help="Maximum number of iterations, ignored if set to zero" type="integer" format="image/tiff, application/x-ogc-envi, application/x-ogc-aaigrid, image/png" /><param name="NOUNDERGROUND" label="Keep Base Level below Surface" help="Keep Base Level below Surface" type="boolean" format="image/tiff, application/x-ogc-envi, application/x-ogc-aaigrid, image/png" /></inputs><outputs><data name="DISTANCE" label="Vertical Distance to Channel Network" /><data name="BASELEVEL" label="Channel Network Base Level" /></outputs></tool>