<tool id="SAGA.grid_filter.8" name="Morphological Filter" version="1.0.0"><description>Morphological filter for grids. Dilation returns the maximum and erosion the minimum value found in a cell's neighbourhood as defined by the kernel. Opening applies first an erosion followed by a dilation and closing is a dilation followed by an erosion. </description><inputs><param name="INPUT" label="Grid" help="Grid" type="text" format="image/tiff, application/x-ogc-envi, application/x-ogc-aaigrid, image/png" /><param name="METHOD" label="Method" help="Choose the operation to perform." type="text" format="image/tiff, application/x-ogc-envi, application/x-ogc-aaigrid, image/png" /><param name="KERNEL_TYPE" label="Kernel Type" help="The shape of the filter kernel." type="text" format="image/tiff, application/x-ogc-envi, application/x-ogc-aaigrid, image/png" /><param name="KERNEL_RADIUS" label="Kernel Radius" help="The kernel radius in cells." type="integer" format="image/tiff, application/x-ogc-envi, application/x-ogc-aaigrid, image/png" /></inputs><outputs><data name="RESULT" label="Filtered Grid" /></outputs></tool>