<tool id="SAGA.statistics_regression.14" name="GWR for Grid Downscaling" version="1.0.0"><description>Geographically Weighted Regression for grid downscaling. </description><inputs><param name="PREDICTORS" label="Predictors" help="Predictors" type="text" format="image/tiff, application/x-ogc-envi, application/x-ogc-aaigrid, image/png" /><param name="DEPENDENT" label="Dependent Variable" help="Dependent Variable" type="text" format="image/tiff, application/x-ogc-envi, application/x-ogc-aaigrid, image/png" /><param name="LOGISTIC" label="Logistic Regression" help="Logistic Regression" type="boolean" format="image/tiff, application/x-ogc-envi, application/x-ogc-aaigrid, image/png" /><param name="MODEL_OUT" label="Output of Model Parameters" help="Output of Model Parameters" type="boolean" format="image/tiff, application/x-ogc-envi, application/x-ogc-aaigrid, image/png" /><param name="SEARCH_RANGE" label="Search Range" help="Search Range" type="text" format="image/tiff, application/x-ogc-envi, application/x-ogc-aaigrid, image/png" /><param name="SEARCH_RADIUS" label="Search Distance [Cells]" help="Search Distance [Cells]" type="integer" format="image/tiff, application/x-ogc-envi, application/x-ogc-aaigrid, image/png" /><param name="DW_WEIGHTING" label="Weighting Function" help="Weighting Function" type="text" format="image/tiff, application/x-ogc-envi, application/x-ogc-aaigrid, image/png" /><param name="DW_IDW_POWER" label="Inverse Distance Weighting Power" help="Inverse Distance Weighting Power" type="float" format="image/tiff, application/x-ogc-envi, application/x-ogc-aaigrid, image/png" /><param name="DW_IDW_OFFSET" label="Inverse Distance Offset" help="Calculates weights for distance plus one, avoiding division by zero for zero distances" type="boolean" format="image/tiff, application/x-ogc-envi, application/x-ogc-aaigrid, image/png" /><param name="DW_BANDWIDTH" label="Gaussian and Exponential Weighting Bandwidth" help="Gaussian and Exponential Weighting Bandwidth" type="float" format="image/tiff, application/x-ogc-envi, application/x-ogc-aaigrid, image/png" /></inputs><outputs><data name="REGRESSION" label="Regression" /><data name="REG_RESCORR" label="Regression with Residual Correction" /><data name="QUALITY" label="Coefficient of Determination" /><data name="RESIDUALS" label="Residuals" /><data name="MODEL" label="Regression Parameters" /></outputs></tool>