<tool id="SAGA.imagery_tools.3" name="Tasseled Cap Transformation" version="1.0.0"><description>Tasseled Cap Transformation as proposed for Landsat Thematic Mapper.</description><inputs><param name="BLUE" label="Blue (TM 1)" help="Blue (TM 1)" type="text" format="image/tiff, application/x-ogc-envi, application/x-ogc-aaigrid, image/png" /><param name="GREEN" label="Green (TM 2)" help="Green (TM 2)" type="text" format="image/tiff, application/x-ogc-envi, application/x-ogc-aaigrid, image/png" /><param name="RED" label="Red (TM 3)" help="Red (TM 3)" type="text" format="image/tiff, application/x-ogc-envi, application/x-ogc-aaigrid, image/png" /><param name="NIR" label="Near Infrared (TM 4)" help="Near Infrared (TM 4)" type="text" format="image/tiff, application/x-ogc-envi, application/x-ogc-aaigrid, image/png" /><param name="MIR1" label="Mid Infrared (TM 5)" help="Mid Infrared (TM 5)" type="text" format="image/tiff, application/x-ogc-envi, application/x-ogc-aaigrid, image/png" /><param name="MIR2" label="Mid Infrared (TM 7)" help="Mid Infrared (TM 7)" type="text" format="image/tiff, application/x-ogc-envi, application/x-ogc-aaigrid, image/png" /></inputs><outputs><data name="BRIGHTNESS" label="Brightness" /><data name="GREENNESS" label="Greenness" /><data name="WETNESS" label="Wetness" /></outputs></tool>